ultrarag.py
ultrarag-1.0.0.dist-info/licenses/LICENSE
ultrarag-1.0.0.dist-info/METADATA
ultrarag-1.0.0.dist-info/WHEEL
ultrarag-1.0.0.dist-info/entry_points.txt
ultrarag-1.0.0.dist-info/top_level.txt
ultrarag-1.0.0.dist-info/RECORD
