Metadata-Version: 2.4
Name: ultrarag
Version: 1.0.0
Summary: Complete RAG with built-in Ollama + FastAPI + Swagger - Zero Config!
Home-page: https://github.com/kumar123ips/ultrarag
Author: Abhishek Kumar
Author-email: ipsabhi420@gmail.com
Keywords: rag llm chatbot ollama fastapi swagger zero-config
Classifier: Development Status :: 5 - Production/Stable
Classifier: Intended Audience :: Developers
Classifier: License :: OSI Approved :: MIT License
Classifier: Programming Language :: Python :: 3.8
Classifier: Programming Language :: Python :: 3.9
Classifier: Programming Language :: Python :: 3.10
Classifier: Programming Language :: Python :: 3.11
Requires-Python: >=3.8
License-File: LICENSE
Requires-Dist: requests>=2.31.0
Provides-Extra: server
Requires-Dist: fastapi>=0.104.1; extra == "server"
Requires-Dist: uvicorn[standard]>=0.24.0; extra == "server"
Requires-Dist: python-multipart>=0.0.6; extra == "server"
Dynamic: author
Dynamic: author-email
Dynamic: classifier
Dynamic: description
Dynamic: description-content-type
Dynamic: home-page
Dynamic: keywords
Dynamic: license-file
Dynamic: provides-extra
Dynamic: requires-dist
Dynamic: requires-python
Dynamic: summary
